odoo/addons/product_custom_info/README.rst
odoo/addons/product_custom_info/__init__.py
odoo/addons/product_custom_info/__manifest__.py
odoo/addons/product_custom_info/i18n/ca.po
odoo/addons/product_custom_info/i18n/es.po
odoo/addons/product_custom_info/i18n/it.po
odoo/addons/product_custom_info/i18n/product_custom_info.pot
odoo/addons/product_custom_info/i18n/pt.po
odoo/addons/product_custom_info/models/__init__.py
odoo/addons/product_custom_info/models/product_product.py
odoo/addons/product_custom_info/models/product_template.py
odoo/addons/product_custom_info/static/description/icon.png
odoo/addons/product_custom_info/views/product_product_view.xml
odoo/addons/product_custom_info/views/product_template_view.xml
odoo13_addon_product_custom_info-13.0.1.0.1.dev7.dist-info/METADATA
odoo13_addon_product_custom_info-13.0.1.0.1.dev7.dist-info/WHEEL
odoo13_addon_product_custom_info-13.0.1.0.1.dev7.dist-info/top_level.txt
odoo13_addon_product_custom_info-13.0.1.0.1.dev7.dist-info/RECORD
